{"assets":{"EE4773A3AABF6F760D236F2370656A88":{"type":"texture","index":36,"assetRequest":{"type":"slide","state":"incoming","slide":"C27AFA4C-D3E3-4F42-AEC3-72CF6D767EE1"},"url":"assets/EE4773A3AABF6F760D236F2370656A88.svg","width":1024,"height":768},"8411FB793A3BC3C4DBEF5ADBCA4AD71F":{"type":"texture","index":35,"assetRequest":{"type":"slide","state":"outgoing","slide":"BBCBF762-7D6A-4C03-8CC0-CFCBB3A48DB5"},"url":"assets/8411FB793A3BC3C4DBEF5ADBCA4AD71F.svg","width":1024,"height":768}},"events":[{"effects":[{"beginTime":0,"baseLayer":{"animations":[],"initialState":{"affineTransform":[1,0,0,1,0,0],"masksToBounds":true,"rotation":0,"scale":1,"position":{"pointX":512,"pointY":384},"width":1024,"sublayerTransform":[1,0,0,0,0,1,0,0,0,0,1,0,0,0,0,1],"contentsRect":{"y":0,"x":0,"width":1,"height":1},"opacity":1,"edgeAntialiasingMask":0,"height":768,"hidden":false,"anchorPoint":{"pointX":0.5,"pointY":0.5}},"objectID":"0","layers":[{"animations":[],"initialState":{"affineTransform":[1,0,0,1,0,0],"masksToBounds":false,"rotation":0,"scale":1,"position":{"pointX":512,"pointY":384},"width":1024,"sublayerTransform":[1,0,0,0,0,1,0,0,0,0,1,-0.0004922987690640373,0,0,0,1],"contentsRect":{"y":0,"x":0,"width":1,"height":1},"opacity":1,"edgeAntialiasingMask":15,"height":768,"hidden":false,"anchorPoint":{"pointX":0.5,"pointY":0.5}},"layers":[{"animations":[],"layers":[],"initialState":{"affineTransform":[1,0,0,1,0,0],"masksToBounds":false,"rotation":0,"scale":1,"position":{"pointX":512,"pointY":384},"width":1024,"sublayerTransform":[1,0,0,0,0,1,0,0,0,0,1,0,0,0,0,1],"contentsRect":{"y":0,"x":0,"width":1,"height":1},"opacity":1,"edgeAntialiasingMask":0,"height":768,"hidden":false,"anchorPoint":{"pointX":0.5,"pointY":0.5}},"texture":"EE4773A3AABF6F760D236F2370656A88"},{"animations":[{"from":{"scalar":false},"beginTime":0,"repeatCount":0,"fillMode":"both","property":"hidden","duration":0.01,"to":{"scalar":true}}],"layers":[],"initialState":{"affineTransform":[1,0,0,1,0,0],"masksToBounds":false,"rotation":0,"scale":1,"position":{"pointX":512,"pointY":384},"width":1024,"sublayerTransform":[1,0,0,0,0,1,0,0,0,0,1,0,0,0,0,1],"contentsRect":{"y":0,"x":0,"width":1,"height":1},"opacity":1,"edgeAntialiasingMask":0,"height":768,"hidden":false,"anchorPoint":{"pointX":0.5,"pointY":0.5}},"texture":"8411FB793A3BC3C4DBEF5ADBCA4AD71F"}]}]},"effects":[],"duration":0.01,"type":"transition","name":"none","objectID":"0"}],"automaticPlay":false,"hyperlinks":[],"accessibility":[{"text":"-270","targetRectangle":{"y":687.5519409179688,"x":166.2914886474609,"width":24.017578125,"height":14}},{"text":"300","targetRectangle":{"y":687.5519409179688,"x":312.9575033187866,"width":20.021484375,"height":14}},{"text":"el1.png","targetRectangle":{"y":173.3796844482422,"x":-77.07225036621094,"width":653.2515258789062,"height":227.5590972900391}},{"text":"Screen Shot 2013-07-25 at 8.41.09 AM.png","targetRectangle":{"y":667.7109336853027,"x":707.128719329834,"width":145,"height":17}},{"text":"20000 yr","targetRectangle":{"y":532.980041384697,"x":4.828320564469323,"width":70.048828125,"height":22}},{"text":"200","targetRectangle":{"y":687.5519409179688,"x":286.9575042724609,"width":20.021484375,"height":14}},{"text":"instantaneous deposition (m)","targetRectangle":{"y":646.7109377384186,"x":670.2963276323862,"width":218.2939453125,"height":20}},{"text":"el4.png","targetRectangle":{"y":433.6419982910156,"x":-70.87337493896484,"width":633.492431640625,"height":220.6760559082031}},{"text":"Screen Shot 2013-07-25 at 8.45.18 AM.png","targetRectangle":{"y":667.5519409179688,"x":177.45751953125,"width":145,"height":18}},{"text":"in1.png","targetRectangle":{"y":143.6786346435547,"x":484.8604431152344,"width":565.5455932617188,"height":289.366455078125}},{"text":"elevation (m)","targetRectangle":{"y":646.0519411563873,"x":199.9177116362844,"width":98.25634765625,"height":20}},{"text":"Tilting ratio (Paola et al., 2001)","targetRectangle":{"y":706.7008056640625,"x":167.0026397705078,"width":264.404,"height":23.44886779785156}},{"text":"ratio of the time scales describing lateral channel mobility to tectonic deformation T*","targetRectangle":{"y":730.7008056640625,"x":167.0026397705078,"width":700.6140000000001,"height":22.47787475585938}},{"text":"in4.png","targetRectangle":{"y":399.2967834472656,"x":484.86865234375,"width":565.545654296875,"height":289.366455078125}},{"text":"fa4.png","targetRectangle":{"y":461.2757301330566,"x":387.9025573730469,"width":234.472823467614,"height":168.03125}},{"text":"35","targetRectangle":{"y":687.7109375,"x":844.7037963867188,"width":13.34765625,"height":14}},{"text":"5000 yr","targetRectangle":{"y":276.159240603447,"x":9.833689531660639,"width":60.0380859375,"height":22}},{"text":"10.8 km","targetRectangle":{"y":383.2855833768845,"x":217.6210790814366,"width":64.0283203125,"height":22}},{"text":"1","targetRectangle":{"y":687.7109375,"x":436.8251953125,"width":6.673828125,"height":14}},{"text":"20","targetRectangle":{"y":687.7109375,"x":784.7037963867188,"width":13.34765625,"height":14}},{"text":"10000","targetRectangle":{"y":687.7109375,"x":553.8056640625,"width":33.369140625,"height":14}},{"text":"Initial phase - Constant sediment flux, no tectonics","targetRectangle":{"y":124,"x":69.29411780834198,"width":539.3960000000001,"height":27.33283996582031}},{"text":" Channels steering by tectonics","targetRectangle":{"y":39.2445068359375,"x":49,"width":610.8059999999997,"height":49.78170776367188}},{"text":"7.5 km","targetRectangle":{"y":260.6713267662562,"x":898.1738280057907,"width":22,"height":54.017578125}},{"text":"Screen Shot 2013-07-25 at 8.44.42 AM.png","targetRectangle":{"y":667.7109375,"x":433.6533203125,"width":145,"height":18}},{"text":"10","targetRectangle":{"y":687.7109375,"x":742.3727416992188,"width":13.34765625,"height":14}},{"text":"0","targetRectangle":{"y":687.5519409179688,"x":247.9633636474609,"width":6.673828125,"height":14}},{"text":"fa1.png","targetRectangle":{"y":203.1436061859131,"x":387.9025573730469,"width":234.4745486664151,"height":168.0323304668418}},{"text":"flow accumulation","targetRectangle":{"y":646.7109377384186,"x":439.3327667738777,"width":135.1201171875,"height":20}},{"text":"0","targetRectangle":{"y":687.7109375,"x":701.7096519470215,"width":6.673828125,"height":14}},{"text":"30","targetRectangle":{"y":687.7109375,"x":824.7037963867188,"width":13.34765625,"height":14}},{"text":"-200","targetRectangle":{"y":687.5519409179688,"x":194.2914886474609,"width":24.017578125,"height":14}}],"baseLayer":{"animations":[],"initialState":{"affineTransform":[1,0,0,1,0,0],"masksToBounds":true,"rotation":0,"scale":1,"position":{"pointX":512,"pointY":384},"width":1024,"sublayerTransform":[1,0,0,0,0,1,0,0,0,0,1,0,0,0,0,1],"contentsRect":{"y":0,"x":0,"width":1,"height":1},"opacity":1,"edgeAntialiasingMask":0,"height":768,"hidden":false,"anchorPoint":{"pointX":0.5,"pointY":0.5}},"objectID":"0","layers":[{"animations":[],"initialState":{"affineTransform":[1,0,0,1,0,0],"masksToBounds":false,"rotation":0,"scale":1,"position":{"pointX":512,"pointY":384},"width":1024,"sublayerTransform":[1,0,0,0,0,1,0,0,0,0,1,-0.0004922987690640373,0,0,0,1],"contentsRect":{"y":0,"x":0,"width":1,"height":1},"opacity":1,"edgeAntialiasingMask":15,"height":768,"hidden":false,"anchorPoint":{"pointX":0.5,"pointY":0.5}},"layers":[{"animations":[],"layers":[],"initialState":{"affineTransform":[1,0,0,1,0,0],"masksToBounds":false,"rotation":0,"scale":1,"position":{"pointX":512,"pointY":384},"width":1024,"sublayerTransform":[1,0,0,0,0,1,0,0,0,0,1,0,0,0,0,1],"contentsRect":{"y":0,"x":0,"width":1,"height":1},"opacity":1,"edgeAntialiasingMask":0,"height":768,"hidden":false,"anchorPoint":{"pointX":0.5,"pointY":0.5}},"texture":"8411FB793A3BC3C4DBEF5ADBCA4AD71F"}]}]}}]}